itk/IOOMEZarrNGFFPython.py
itk/_IOOMEZarrNGFFPython.pyd
itk/__init_ioomezarrngff__.py
itk/itkOMEZarrNGFFImageIOPython.py
itk/Configuration/IOOMEZarrNGFFConfig.py
itk/Configuration/IOOMEZarrNGFF_snake_case.py
itk_ioomezarrngff-0.3.0.dist-info/licenses/LICENSE
itk_ioomezarrngff.libs/.load-order-itk_ioomezarrngff-0.3.0
itk_ioomezarrngff.libs/msvcp140.dll
itk_ioomezarrngff.libs/vcruntime140_1.dll
itk_ioomezarrngff-0.3.0.dist-info/DELVEWHEEL
itk_ioomezarrngff-0.3.0.dist-info/METADATA
itk_ioomezarrngff-0.3.0.dist-info/WHEEL
itk_ioomezarrngff-0.3.0.dist-info/RECORD
